cryptopkg/__init__.py
cryptopkg/constants.py
cryptopkg/crypto.py
cryptopkg-0.1.0.dist-info/METADATA
cryptopkg-0.1.0.dist-info/WHEEL
cryptopkg-0.1.0.dist-info/top_level.txt
cryptopkg-0.1.0.dist-info/RECORD
