Metadata-Version: 2.4
Name: cryptopkg
Version: 0.1.0
Summary: A universal package for symmetric encryption (AES-GCM) and hashing (SHA256).
Author-email: Grigor Khachatryan <grigor777001@yandex.ru>
Requires-Python: >=3.7
Requires-Dist: pycryptodome>=3.19.0
